plananalyze/__init__.py
plananalyze/cli.py
plananalyze/core.py
plananalyze/exceptions.py
plananalyze/models.py
plananalyze/analyzers/__init__.py
plananalyze/analyzers/bottlenecks.py
plananalyze/analyzers/performance.py
plananalyze/analyzers/recommendations.py
plananalyze/formatters/__init__.py
plananalyze/formatters/html.py
plananalyze/formatters/json.py
plananalyze/formatters/text.py
plananalyze/parsers/__init__.py
plananalyze/parsers/base.py
plananalyze/parsers/json_parser.py
plananalyze/parsers/text_parser.py
plananalyze/parsers/xml_parser.py
plananalyze/utils/__init__.py
plananalyze/utils/constants.py
plananalyze/utils/helpers.py
plananalyze-0.1.0.dist-info/licenses/LICENSE
plananalyze-0.1.0.dist-info/METADATA
plananalyze-0.1.0.dist-info/WHEEL
plananalyze-0.1.0.dist-info/entry_points.txt
plananalyze-0.1.0.dist-info/top_level.txt
plananalyze-0.1.0.dist-info/RECORD
